ktnumpy/ktnumpy.cp36-win_amd64.exp
ktnumpy/ktnumpy.cp36-win_amd64.lib
ktnumpy/ktnumpy.cp36-win_amd64.pyd
ktnumpy/ktnumpy.dll
ktnumpy-0.1.5.dist-info/LICENSE
ktnumpy-0.1.5.dist-info/METADATA
ktnumpy-0.1.5.dist-info/WHEEL
ktnumpy-0.1.5.dist-info/top_level.txt
ktnumpy-0.1.5.dist-info/RECORD
